[
  {
    "_id": 1,
    "team1": "Bangladesh",
    "team1Flag": "https://upload.wikimedia.org/wikipedia/commons/thumb/f/f9/Flag_of_Bangladesh.svg/1200px-Flag_of_Bangladesh.svg.png",
    "team2": "India",
    "team2Flag": "https://upload.wikimedia.org/wikipedia/en/thumb/4/41/Flag_of_India.svg/1200px-Flag_of_India.svg.png",
    "time": "01:00 PM",
    "date": "20-12-22",
    "matchs": "World T20"
  },
  {
    "_id": 2,
    "team1": "Pakisthan",
    "team1Flag": "https://www.flagcolorcodes.com/data/flag-of-pakistan.png",
    "team2": "Australia",
    "team2Flag": "https://img.freepik.com/premium-vector/flag-usa-united-states-america-background_53500-169.jpg?w=2000",
    "time": "09:00 PM",
    "date": "21-12-22",
    "matchs": "World T20"
  },
  {
    "_id": 3,
    "team1": "England",
    "team1Flag": "https://i.ibb.co/km2sqBt/england.png",
    "team2": "India",
    "team2Flag": "https://upload.wikimedia.org/wikipedia/en/thumb/4/41/Flag_of_India.svg/1200px-Flag_of_India.svg.png",
    "time": "02:00 PM",
    "date": "22-12-22",
    "matchs": "World T20"
  },
  {
    "_id": 4,
    "team1": "Pakisthan",
    "team1Flag": "https://www.flagcolorcodes.com/data/flag-of-pakistan.png",
    "team2": "Bangladesh",
    "team2Flag": "https://upload.wikimedia.org/wikipedia/commons/thumb/f/f9/Flag_of_Bangladesh.svg/1200px-Flag_of_Bangladesh.svg.png",
    "time": "02:00 PM",
    "date": "23-12-22",
    "matchs": "World T20"
  },
  {
    "_id": 5,
    "team1": "South Africa ",
    "team1Flag": "https://cdn.britannica.com/27/4227-050-00DBD10A/Flag-South-Africa.jpg",
    "team2": "Afganistan",
    "team2Flag": "https://cdn.britannica.com/40/5340-004-B25ED5CF/Flag-Afghanistan.jpg",
    "time": "02:00 PM",
    "date": "24-12-22",
    "matchs": "World T20"
  },
  {
    "_id": 6,
    "team1": "West Indies",
    "team1Flag": "https://external-preview.redd.it/Cb8DeVEQy4xeuaGx-inr2gdzWlgaNuDZVLrMKtSTU7c.png?auto=webp&s=7334e11f1232fc4df736e30db053e45e543192da",
    "team2": "New Zealand",
    "team2Flag": "https://img.freepik.com/premium-vector/realistic-national-flag-new-zealand_73458-1480.jpg?w=2000",
    "time": "02:00 PM",
    "date": "25-12-22",
    "matchs": "World T20"
  }
]
